/*
 * Created on 16/11/2008
 *
 * TODO To change the template for this generated file go to
 * Window - Preferences - Java - Code Style - Code Templates
 */

package com.antiaction.classfile.bytecode;

public class Opcodes {

	public static final int OPCODE_NOP = 0;				// 0x00
	public static final int OPCODE_ACONST_NULL = 1;		// 0x01
	public static final int OPCODE_ICONST_M1 = 2;		// 0x02
	public static final int OPCODE_ICONST_0 = 3;		// 0x03
	public static final int OPCODE_ICONST_1 = 4;		// 0x04
	public static final int OPCODE_ICONST_2 = 5;		// 0x05
	public static final int OPCODE_ICONST_3 = 6;		// 0x06
	public static final int OPCODE_ICONST_4 = 7;		// 0x07
	public static final int OPCODE_ICONST_5 = 8;		// 0x08
	public static final int OPCODE_LCONST_0 = 9;		// 0x09
	public static final int OPCODE_LCONST_1 = 10;		// 0x0a
	public static final int OPCODE_FCONST_0 = 11;		// 0x0b
	public static final int OPCODE_FCONST_1 = 12;		// 0x0c
	public static final int OPCODE_FCONST_2 = 13;		// 0x0d
	public static final int OPCODE_DCONST_0 = 14;		// 0x0e
	public static final int OPCODE_DCONST_1 = 15;		// 0x0f
	public static final int OPCODE_BIPUSH = 16;			// 0x10
	public static final int OPCODE_SIPUSH = 17;			// 0x11
	public static final int OPCODE_LDC = 18;			// 0x12
	public static final int OPCODE_LDC_W = 19;			// 0x13
	public static final int OPCODE_LDC2_W = 20;			// 0x14
	public static final int OPCODE_ILOAD = 21;			// 0x15
	public static final int OPCODE_LLOAD = 22;			// 0x16
	public static final int OPCODE_FLOAD = 23;			// 0x17
	public static final int OPCODE_DLOAD = 24;			// 0x18
	public static final int OPCODE_ALOAD = 25;			// 0x19
	public static final int OPCODE_ILOAD_0 = 26;		// 0x1a
	public static final int OPCODE_ILOAD_1 = 27;		// 0x1b
	public static final int OPCODE_ILOAD_2 = 28;		// 0x1c
	public static final int OPCODE_ILOAD_3 = 29;		// 0x1d
	public static final int OPCODE_LLOAD_0 = 30;		// 0x1e
	public static final int OPCODE_LLOAD_1 = 31;		// 0x1f
	public static final int OPCODE_LLOAD_2 = 32;		// 0x20
	public static final int OPCODE_LLOAD_3 = 33;		// 0x21
	public static final int OPCODE_FLOAD_0 = 34;		// 0x22
	public static final int OPCODE_FLOAD_1 = 35;		// 0x23
	public static final int OPCODE_FLOAD_2 = 36;		// 0x24
	public static final int OPCODE_FLOAD_3 = 37;		// 0x25
	public static final int OPCODE_DLOAD_0 = 38;		// 0x26
	public static final int OPCODE_DLOAD_1 = 39;		// 0x27
	public static final int OPCODE_DLOAD_2 = 40;		// 0x28
	public static final int OPCODE_DLOAD_3 = 41;		// 0x29
	public static final int OPCODE_ALOAD_0 = 42;		// 0x2a
	public static final int OPCODE_ALOAD_1 = 43;		// 0x2b
	public static final int OPCODE_ALOAD_2 = 44;		// 0x2c
	public static final int OPCODE_ALOAD_3 = 45;		// 0x2d
	public static final int OPCODE_IALOAD = 46;			// 0x2e
	public static final int OPCODE_LALOAD = 47;			// 0x2f
	public static final int OPCODE_FALOAD = 48;			// 0x30
	public static final int OPCODE_DALOAD = 49;			// 0x31
	public static final int OPCODE_AALOAD = 50;			// 0x32
	public static final int OPCODE_BALOAD = 51;			// 0x33
	public static final int OPCODE_CALOAD = 52;			// 0x34
	public static final int OPCODE_SALOAD = 53;			// 0x35
	public static final int OPCODE_ISTORE = 54;			// 0x36
	public static final int OPCODE_LSTORE = 55;			// 0x37
	public static final int OPCODE_FSTORE = 56;			// 0x38
	public static final int OPCODE_DSTORE = 57;			// 0x39
	public static final int OPCODE_ASTORE = 58;			// 0x3a
	public static final int OPCODE_ISTORE_0 = 59;		// 0x3b
	public static final int OPCODE_ISTORE_1 = 60;		// 0x3c
	public static final int OPCODE_ISTORE_2 = 61;		// 0x3d
	public static final int OPCODE_ISTORE_3 = 62;		// 0x3e
	public static final int OPCODE_LSTORE_0 = 63;		// 0x3f
	public static final int OPCODE_LSTORE_1 = 64;		// 0x40
	public static final int OPCODE_LSTORE_2 = 65;		// 0x41
	public static final int OPCODE_LSTORE_3 = 66;		// 0x42
	public static final int OPCODE_FSTORE_0 = 67;		// 0x43
	public static final int OPCODE_FSTORE_1 = 68;		// 0x44
	public static final int OPCODE_FSTORE_2 = 69;		// 0x45
	public static final int OPCODE_FSTORE_3 = 70;		// 0x46
	public static final int OPCODE_DSTORE_0 = 71;		// 0x47
	public static final int OPCODE_DSTORE_1 = 72;		// 0x48
	public static final int OPCODE_DSTORE_2 = 73;		// 0x49
	public static final int OPCODE_DSTORE_3 = 74;		// 0x4a
	public static final int OPCODE_ASTORE_0 = 75;		// 0x4b
	public static final int OPCODE_ASTORE_1 = 76;		// 0x4c
	public static final int OPCODE_ASTORE_2 = 77;		// 0x4d
	public static final int OPCODE_ASTORE_3 = 78;		// 0x4e
	public static final int OPCODE_IASTORE = 79;		// 0x4f
	public static final int OPCODE_LASTORE = 80;		// 0x50
	public static final int OPCODE_FASTORE = 81;		// 0x51
	public static final int OPCODE_DASTORE = 82;		// 0x52
	public static final int OPCODE_AASTORE = 83;		// 0x53
	public static final int OPCODE_BASTORE = 84;		// 0x54
	public static final int OPCODE_CASTORE = 85;		// 0x55
	public static final int OPCODE_SASTORE = 86;		// 0x56
	public static final int OPCODE_POP = 87;			// 0x57
	public static final int OPCODE_POP2 = 88;			// 0x58
	public static final int OPCODE_DUP = 89;			// 0x59
	public static final int OPCODE_DUP_X1 = 90;			// 0x5a
	public static final int OPCODE_DUP_X2 = 91;			// 0x5b
	public static final int OPCODE_DUP2 = 92;			// 0x5c
	public static final int OPCODE_DUP2_X1 = 93;		// 0x5d
	public static final int OPCODE_DUP2_X2 = 94;		// 0x5e
	public static final int OPCODE_SWAP = 95;			// 0x5f
	public static final int OPCODE_IADD = 96;			// 0x60
	public static final int OPCODE_LADD = 97;			// 0x61
	public static final int OPCODE_FADD = 98;			// 0x62
	public static final int OPCODE_DADD = 99;			// 0x63
	public static final int OPCODE_ISUB = 100;			// 0x64
	public static final int OPCODE_LSUB = 101;			// 0x65
	public static final int OPCODE_FSUB = 102;			// 0x66
	public static final int OPCODE_DSUB = 103;			// 0x67
	public static final int OPCODE_IMUL = 104;			// 0x68
	public static final int OPCODE_LMUL = 105;			// 0x69
	public static final int OPCODE_FMUL = 106;			// 0x6a
	public static final int OPCODE_DMUL = 107;			// 0x6b
	public static final int OPCODE_IDIV = 108;			// 0x6c
	public static final int OPCODE_LDIV = 109;			// 0x6d
	public static final int OPCODE_FDIV = 110;			// 0x6e
	public static final int OPCODE_DDIV = 111;			// 0x6f
	public static final int OPCODE_IREM = 112;			// 0x70
	public static final int OPCODE_LREM = 113;			// 0x71
	public static final int OPCODE_FREM = 114;			// 0x72
	public static final int OPCODE_DREM = 115;			// 0x73
	public static final int OPCODE_INEG = 116;			// 0x74
	public static final int OPCODE_LNEG = 117;			// 0x75
	public static final int OPCODE_FNEG = 118;			// 0x76
	public static final int OPCODE_DNEG = 119;			// 0x77
	public static final int OPCODE_ISHL = 120;			// 0x78
	public static final int OPCODE_LSHL = 121;			// 0x79
	public static final int OPCODE_ISHR = 122;			// 0x7a
	public static final int OPCODE_LSHR = 123;			// 0x7b
	public static final int OPCODE_IUSHR = 124;			// 0x7c
	public static final int OPCODE_LUSHR = 125;			// 0x7d
	public static final int OPCODE_IAND = 126;			// 0x7e
	public static final int OPCODE_LAND = 127;			// 0x7f
	public static final int OPCODE_IOR = 128;			// 0x80
	public static final int OPCODE_LOR = 129;			// 0x81
	public static final int OPCODE_IXOR = 130;			// 0x82
	public static final int OPCODE_LXOR = 131;			// 0x83
	public static final int OPCODE_IINC = 132;			// 0x84
	public static final int OPCODE_I2L = 133;			// 0x85
	public static final int OPCODE_I2F = 134;			// 0x86
	public static final int OPCODE_I2D = 135;			// 0x87
	public static final int OPCODE_L2I = 136;			// 0x88
	public static final int OPCODE_L2F = 137;			// 0x89
	public static final int OPCODE_L2D = 138;			// 0x8a
	public static final int OPCODE_F2I = 139;			// 0x8b
	public static final int OPCODE_F2L = 140;			// 0x8c
	public static final int OPCODE_F2D = 141;			// 0x8d
	public static final int OPCODE_D2I = 142;			// 0x8e
	public static final int OPCODE_D2L = 143;			// 0x8f
	public static final int OPCODE_D2F = 144;			// 0x90
	public static final int OPCODE_I2B = 145;			// 0x91
	public static final int OPCODE_I2C = 146;			// 0x92
	public static final int OPCODE_I2S = 147;			// 0x93
	public static final int OPCODE_LCMP = 148;			// 0x94
	public static final int OPCODE_FCMPL = 149;			// 0x95
	public static final int OPCODE_FCMPG = 150;			// 0x96
	public static final int OPCODE_DCMPL = 151;			// 0x97
	public static final int OPCODE_DCMPG = 152;			// 0x98
	public static final int OPCODE_IFEQ = 153;			// 0x99
	public static final int OPCODE_IFNE = 154;			// 0x9a
	public static final int OPCODE_IFLT = 155;			// 0x9b
	public static final int OPCODE_IFGE = 156;			// 0x9c
	public static final int OPCODE_IFGT = 157;			// 0x9d
	public static final int OPCODE_IFLE = 158;			// 0x9e
	public static final int OPCODE_IF_ICMPEQ = 159;		// 0x9f
	public static final int OPCODE_IF_ICMPNE = 160;		// 0xa0
	public static final int OPCODE_IF_ICMPLT = 161;		// 0xa1
	public static final int OPCODE_IF_ICMPGE = 162;		// 0xa2
	public static final int OPCODE_IF_ICMPGT = 163;		// 0xa3
	public static final int OPCODE_IF_ICMPLE = 164;		// 0xa4
	public static final int OPCODE_IF_ACMPEQ = 165;		// 0xa5
	public static final int OPCODE_IF_ACMPNE = 166;		// 0xa6
	public static final int OPCODE_GOTO = 167;			// 0xa7
	public static final int OPCODE_JSR = 168;			// 0xa8
	public static final int OPCODE_RET = 169;			// 0xa9
	public static final int OPCODE_TABLESWITCH = 170;	// 0xaa
	public static final int OPCODE_LOOKUPSWITCH = 171;	// 0xab
	public static final int OPCODE_IRETURN = 172;		// 0xac
	public static final int OPCODE_LRETURN = 173;		// 0xad
	public static final int OPCODE_FRETURN = 174;		// 0xae
	public static final int OPCODE_DRETURN = 175;		// 0xaf
	public static final int OPCODE_ARETURN = 176;		// 0xb0
	public static final int OPCODE_RETURN = 177;		// 0xb1
	public static final int OPCODE_GETSTATIC = 178;		// 0xb2
	public static final int OPCODE_PUTSTATIC = 179;		// 0xb3
	public static final int OPCODE_GETFIELD = 180;		// 0xb4
	public static final int OPCODE_PUTFIELD = 181;		// 0xb5
	public static final int OPCODE_INVOKEVIRTUAL = 182;		// 0xb6
	public static final int OPCODE_INVOKESPECIAL = 183;		// 0xb7
	public static final int OPCODE_INVOKESTATIC = 184;		// 0xb8
	public static final int OPCODE_INVOKEINTERFACE = 185;	// 0xb9
	public static final int OPCODE_NEW = 187;			// 0xbb
	public static final int OPCODE_NEWARRAY = 188;		// 0xbc
	public static final int OPCODE_ANEWARRAY = 189;		// 0xbd
	public static final int OPCODE_ARRAYLENGTH = 190;	// 0xbe
	public static final int OPCODE_ATHROW = 191;		// 0xbf
	public static final int OPCODE_CHECKCAST = 192;		// 0xc0
	public static final int OPCODE_INSTANCEOF = 193;	// 0xc1
	public static final int OPCODE_MONITORENTER = 194;	// 0xc2
	public static final int OPCODE_MONITOREXIT = 195;	// 0xc3
	public static final int OPCODE_WIDE = 196;			// 0xc4
	public static final int OPCODE_MULTINEWARRAY = 197;	// 0xc5
	public static final int OPCODE_IFNULL = 198;		// 0xc6
	public static final int OPCODE_IFNONNULL = 199;		// 0xc7
	public static final int OPCODE_GOTO_W = 200;		// 0xc8
	public static final int OPCODE_JSR_W = 201;			// 0xc9
	//public static final int OPCODE_ = ;		//

}
